spce/__init__.py
spce/avro.py
spce/cloudevents.py
spce/json.py
spce-0.3.0.dist-info/LICENSE
spce-0.3.0.dist-info/METADATA
spce-0.3.0.dist-info/WHEEL
spce-0.3.0.dist-info/top_level.txt
spce-0.3.0.dist-info/RECORD
