Metadata-Version: 2.1
Name: spce
Version: 0.3.0
Summary: ScalePlan's CloudEvents implementation
Home-page: https://github.com/scaleplandev/spce-python
Author: ScalePlan Engineering
Author-email: dev@scaleplan.io
License: Apache 2.0
Keywords: cloudevents,scaleplan,cloud,events,event
Platform: UNKNOWN
Classifier: Development Status :: 4 - Beta
Classifier: Intended Audience :: Developers
Classifier: License :: OSI Approved :: Apache Software License
Classifier: Programming Language :: Python :: 3
Classifier: Programming Language :: Python :: 3.6
Classifier: Programming Language :: Python :: 3.7
Classifier: Programming Language :: Python :: 3.8
Classifier: Operating System :: OS Independent
Provides-Extra: avro
Requires-Dist: avro (>=1.10) ; extra == 'avro'
